magnetos/__init__.py
magnetos/cracker/__init__.py
magnetos/cracker/steg_hide_cracker.py
magnetos/crypto/__init__.py
magnetos/crypto/caesar.py
magnetos/crypto/caesar_odd_even.py
magnetos/crypto/caesar_printable.py
magnetos/crypto/caesar_rail_fence_crack.py
magnetos/crypto/mobile_keyboard.py
magnetos/crypto/polybius_square_cipher.py
magnetos/crypto/quoted_printable.py
magnetos/crypto/qwerty_cipher.py
magnetos/crypto/rail_fence_cipher.py
magnetos/crypto/rc4.py
magnetos/crypto/rot13.py
magnetos/crypto/shadow_code.py
magnetos/crypto/vigenere_cipher.py
magnetos/crypto/xxencode.py
magnetos/fuzzing/__init__.py
magnetos/fuzzing/what_code_scheme.py
magnetos/fuzzing/what_encode.py
magnetos/fuzzing/what_format.py
magnetos/fuzzing/what_steg.py
magnetos/fuzzing/data/what_format.dic
magnetos/proxy/__init__.py
magnetos/proxy/reverse_proxy.py
magnetos/utils/__init__.py
magnetos/utils/converter.py
magnetos/utils/file_hash.py
magnetos/utils/file_strings.py
magnetos/utils/find_ctf_flag.py
magnetos/utils/string_utils.py
magnetos/utils/web_get.py
tests/__init__.py
tests/test_converter.py
tests/test_crypto.py
tests/test_find_ctf_flag.py
tests/test_what_encode.py
magnetos-0.8.0.dist-info/LICENSE
magnetos-0.8.0.dist-info/METADATA
magnetos-0.8.0.dist-info/WHEEL
magnetos-0.8.0.dist-info/entry_points.txt
magnetos-0.8.0.dist-info/top_level.txt
magnetos-0.8.0.dist-info/zip-safe
magnetos-0.8.0.dist-info/RECORD
